{
  "environments": {
    "gitlab_server": {
      "description": "GitLab server environment (Ubuntu machine with GitLab access)",
      "paths": {
        "repo_dir": "/work/develop_gitlab/slam-core",
        "bundles_dir": "/work/develop_gitlab/slam-core/bundles",
        "local_bundles_dir": "./local-bundles",
        "backup_dir": "/work/develop_gitlab/slam-core-backups"
      },
      "git": {
        "user_name": "Your Name",
        "user_email": "your.email@company.com",
        "allow_protocol": "file"
      },
      "sync": {
        "backup_before_update": true,
        "create_diff_report": true,
        "auto_resolve_conflicts": false,
        "confirm_before_actions": true
      }
    },
    "offline_windows": {
      "description": "Windows offline development environment (Windows machine without GitLab access)",
      "paths": {
        "repo_dir": "D:/Projects/tmp/slam-core",
        "bundles_dir": "D:/Work/code/2025/0625/bundles",
        "local_bundles_dir": "D:/Projects/tmp/local-bundles",
        "backup_dir": "D:/Projects/tmp/slam-core"
      },
      "git": {
        "user_name": "Your Name",
        "user_email": "your.email@company.com",
        "allow_protocol": "file"
      },
      "sync": {
        "backup_before_update": true,
        "create_diff_report": true,
        "auto_resolve_conflicts": false,
        "confirm_before_actions": true
      }
    },
    "offline_ubuntu": {
      "description": "Ubuntu offline development environment (Ubuntu machine without GitLab access)",
      "paths": {
        "repo_dir": "/work/develop_gitlab/slam-core",
        "bundles_dir": "/work/develop_gitlab/slam-core/bundles",
        "local_bundles_dir": "./local-bundles",
        "backup_dir": "/work/develop_gitlab/slam-core-backups"
      },
      "git": {
        "user_name": "Your Name",
        "user_email": "your.email@company.com",
        "allow_protocol": "file"
      },
      "sync": {
        "backup_before_update": true,
        "create_diff_report": true,
        "auto_resolve_conflicts": false,
        "confirm_before_actions": true
      }
    }
  },
  "global": {
    "description": "Global configuration (shared by all environments)",
    "bundle": {
      "include_all_branches": false,
      "timestamp_format": "yyyyMMdd_HHmmss",
      "local_prefix": "local_",
      "main_repo_name": "slam-core"
    },
    "workflow": {
      "auto_create_local_bundle": false,
      "enable_interactive_mode": true,
      "show_detailed_status": true
    },
    "platform": {
      "detect_automatically": true,
      "force_platform": null
    }
  }
} 